{
  "conditions": [
    {
      "type": "isValid",
      "modid": "ic2"
    }
  ],
  "type": "forge:ore_shaped",
  "pattern": [
    "mSn",
    "ExE",
    "EDE"
  ],
  "key": {
    "E": {
      "item": "#CARBON_PLATE"
    },
    "x": {
      "item": "#FORCEPOWER_CRYSTAL"
    },
    "D": {
      "item": "#ADVANCED_CIRCUIT"
    },
    "m": {
      "item": "minecraft:redstone"
    },
    "S": {
      "item": "ic2:wrench"
    },
    "n": {
      "item": "minecraft:lever"
    }
  },
  "result": {
    "item": "modularforcefieldsystem:multitool_wrench",
    "data": 101,
    "count": 1,
    "nbt": {
      "ForceEnergy": 0
    }
  }
}